{
	"info": {
		"_postman_id": "14daa8e7-f983-4cd8-a9d1-3ab39d7ec906",
		"name": "OOP Final",
		"schema": "https://schema.getpostman.com/json/collection/v2.1.0/collection.json"
	},
	"item": [
		{
			"name": "Sign In",
			"request": {
				"method": "POST",
				"header": [],
				"body": {
					"mode": "raw",
					"raw": "{\r\n    \"username\": \"test1\",\r\n    \"password\": \"123456\"\r\n}",
					"options": {
						"raw": {
							"language": "json"
						}
					}
				},
				"url": {
					"raw": "http://localhost:8080/api/auth/signin",
					"protocol": "http",
					"host": [
						"localhost"
					],
					"port": "8080",
					"path": [
						"api",
						"auth",
						"signin"
					]
				},
				"description": "Sign in to access other APIs"
			},
			"response": []
		},
		{
			"name": "Sign up",
			"request": {
				"method": "POST",
				"header": [],
				"body": {
					"mode": "raw",
					"raw": "{\r\n    \"username\": \"test1\",\r\n    \"email\": \"test1@smu.com\",\r\n    \"password\": \"123456\",\r\n    \"role\": [\"user\"]\r\n}",
					"options": {
						"raw": {
							"language": "json"
						}
					}
				},
				"url": {
					"raw": "http://localhost:8080/api/auth/signup",
					"protocol": "http",
					"host": [
						"localhost"
					],
					"port": "8080",
					"path": [
						"api",
						"auth",
						"signup"
					]
				},
				"description": "Insert a new entry into corporate_user table (4 Param)"
			},
			"response": []
		},
		{
			"name": "Get all Corporate Fields by corporate_user_id",
			"protocolProfileBehavior": {
				"disableBodyPruning": true
			},
			"request": {
				"method": "GET",
				"header": [],
				"body": {
					"mode": "formdata",
					"formdata": []
				},
				"url": {
					"raw": "http://localhost:8080/api/getAllCorpFieldByCorpUserId/8",
					"protocol": "http",
					"host": [
						"localhost"
					],
					"port": "8080",
					"path": [
						"api",
						"getAllCorpFieldByCorpUserId",
						"8"
					]
				},
				"description": "Retrieves all fields associated to a Corporate User"
			},
			"response": []
		},
		{
			"name": "Get Excel Header",
			"request": {
				"method": "POST",
				"header": [],
				"body": {
					"mode": "formdata",
					"formdata": [
						{
							"key": "file",
							"type": "file",
							"src": "/C:/Users/shgan/Downloads/SMU S3T2/IS442 - Object Oriented Programming - G2/Project/frontend/src/data/SMU DUMMY DATA.xlsx"
						}
					]
				},
				"url": {
					"raw": "http://localhost:8080/api/uploadExcelHeader/1/2",
					"protocol": "http",
					"host": [
						"localhost"
					],
					"port": "8080",
					"path": [
						"api",
						"uploadExcelHeader",
						"1",
						"2"
					]
				}
			},
			"response": []
		},
		{
			"name": "Add new Field Mapping",
			"request": {
				"method": "POST",
				"header": [],
				"body": {
					"mode": "raw",
					"raw": "[\r\n    {\r\n        \"corporateFieldId\" : 1,\r\n        \"apiFieldId\" : 1\r\n    },\r\n    {\r\n    \"corporateFieldId\" : 2,\r\n    \"apiFieldId\" : 2\r\n    }\r\n]",
					"options": {
						"raw": {
							"language": "json"
						}
					}
				},
				"url": {
					"raw": "http://localhost:8080/api/addFieldMapping/",
					"protocol": "http",
					"host": [
						"localhost"
					],
					"port": "8080",
					"path": [
						"api",
						"addFieldMapping",
						""
					]
				},
				"description": "Insert a new entry into field_mapping table (2 Param)"
			},
			"response": []
		},
		{
			"name": "Upload Field Mapping",
			"request": {
				"method": "POST",
				"header": [],
				"body": {
					"mode": "formdata",
					"formdata": [
						{
							"key": "file",
							"type": "file",
							"src": "/D:/Yu Quan/Downloads/SMU DUMMY DATA.xlsx"
						}
					]
				},
				"url": {
					"raw": "http://localhost:8080/api/uploadFieldMapping/4/24",
					"protocol": "http",
					"host": [
						"localhost"
					],
					"port": "8080",
					"path": [
						"api",
						"uploadFieldMapping",
						"4",
						"24"
					],
					"query": [
						{
							"key": null,
							"value": "",
							"disabled": true
						}
					]
				}
			},
			"response": []
		},
		{
			"name": "Sign Out",
			"request": {
				"method": "POST",
				"header": [],
				"url": {
					"raw": "localhost:8080/api/auth/signout",
					"host": [
						"localhost"
					],
					"port": "8080",
					"path": [
						"api",
						"auth",
						"signout"
					]
				},
				"description": "Signs out user and remove associated cookie"
			},
			"response": []
		}
	]
}